{
	"-ms-height": "fixed",
	"body": [{
		"selectAction": {
			"title": "Open In Bing",
			"url": "https://www.bing.com/search?q=Microsoft+stock.&elv=AXXfrEiqqD9r3GuelwApulrl!col*6AWacG3XVaSlhQgzsiuP*rcLsid4WIMaXj!VGazs4UAQNQo*ZwgYRPYhpBscEsz4s8r9uuW6alYn6Jw",
			"type": "Action.OpenUrl"
		},
		"items": [{
			"items": [{
				"separation": "none",
				"isSubtle": true,
				"spacing": "none",
				"size": "small",
				"text": "Microsoft Corp (NASDAQ: MSFT)",
				"type": "TextBlock"
			}, {
				"separation": "none",
				"isSubtle": true,
				"spacing": "none",
				"size": "small",
				"text": "June 14, 7:59 PM EDT",
				"type": "TextBlock"
			}],
			"type": "Container"
		}, {
			"items": [{
				"columns": [{
					"items": [{
						"textStyle": "display",
						"size": "extraLarge",
						"text": "101.42",
						"type": "TextBlock"
					}, {
						"color": "attention",
						"text": "▲ 0.570 (0.565%)",
						"type": "TextBlock"
					}],
					"width": "auto",
					"type": "Column"
				}, {
					"spacing": "extraLarge",
					"items": [],
					"width": "stretch",
					"type": "Column"
				}],
				"type": "ColumnSet"
			}],
			"type": "Container"
		}],
		"height": "stretch",
		"type": "Container"
	}],
	"-ms-source": "Bing",
	"version": "1.0",
	"type": "AdaptiveCard"
}